[
  {
    "applicationNumber": "1020200127054",
    "receiptSendSerialNumber": "1",
    "receiptSendNumber": "112020104017278",
    "petitionclauseNumber": "1",
    "changeTypeCode": "I",
    "changeTypeName": "신규",
    "petitionclause": "원료 고무 100 중량부; 및<br />보강성 충진제 90 내지 140 중량부를 포함하되,<br />상기 원료 고무는, <br />고시스 네오디뮴 부타디엔 고무(Nd-BR) 25 내지 65 중량부, 고기능성 리튬 부타디엔 고무(Functionalized Li-BR) 5 내지 45 중량부, 및 용액 중합 스티렌-부타디엔 고무 20 내지 50중량부를 포함하는 타이어 트레드용 고무 조성물.",
    "transferReceiptDocNumber": " ",
    "transferPetitionclause": " "
  },
  {
    "applicationNumber": "1020200127054",
    "receiptSendSerialNumber": "1",
    "receiptSendNumber": "112020104017278",
    "petitionclauseNumber": "2",
    "changeTypeCode": "I",
    "changeTypeName": "신규",
    "petitionclause": "제 1항에 있어서,<br />상기 용액 중합 스티렌-부타디엔 고무는, 스티렌 함량이 20 내지 40중량% 및 비닐 함량이 10 내지 40 중량%를 포함하는 타이어 트레드용 고무 조성물.",
    "transferReceiptDocNumber": " ",
    "transferPetitionclause": " "
  },
  {
    "applicationNumber": "1020200127054",
    "receiptSendSerialNumber": "1",
    "receiptSendNumber": "112020104017278",
    "petitionclauseNumber": "3",
    "changeTypeCode": "I",
    "changeTypeName": "신규",
    "petitionclause": "제 1항에 있어서,<br />상기 고시스 네오디뮴 부타디엔 고무는 시스 함량이 96% 이상이고,<br />상기 고기능성 리튬 부타디엔 고무는 비닐(vinyl) 함량이 10 내지 40 중량%인 타이어 트레드용 고무 조성물.",
    "transferReceiptDocNumber": " ",
    "transferPetitionclause": " "
  },
  {
    "applicationNumber": "1020200127054",
    "receiptSendSerialNumber": "1",
    "receiptSendNumber": "112020104017278",
    "petitionclauseNumber": "4",
    "changeTypeCode": "I",
    "changeTypeName": "신규",
    "petitionclause": "제 1항에 있어서,<br />상기 보강성 충진제는, 상기 원료 고무 100 중량부에 대하여 실리카 85 내지 120 중량부 및 카본 블랙 5 내지 20중량부를 포함하는 타이어 트레드용 고무 조성물.",
    "transferReceiptDocNumber": " ",
    "transferPetitionclause": " "
  },
  {
    "applicationNumber": "1020200127054",
    "receiptSendSerialNumber": "1",
    "receiptSendNumber": "112020104017278",
    "petitionclauseNumber": "5",
    "changeTypeCode": "I",
    "changeTypeName": "신규",
    "petitionclause": "제 1항에 있어서,<br />상기 고시스 네오디뮴 부타디엔 고무의 중량 평균 분자량(Mw)은 30만 내지 60만 g/mol인 타이어 트레드용 고무 조성물.",
    "transferReceiptDocNumber": " ",
    "transferPetitionclause": " "
  },
  {
    "applicationNumber": "1020200127054",
    "receiptSendSerialNumber": "1",
    "receiptSendNumber": "112020104017278",
    "petitionclauseNumber": "6",
    "changeTypeCode": "I",
    "changeTypeName": "신규",
    "petitionclause": "제 1항에 있어서,<br />상기 고기능성 리튬 부타디엔 고무의 중량 평균 분자량(Mw)은 10만 내지 30만 g/mol인 타이어 트레드용 고무 조성물.",
    "transferReceiptDocNumber": " ",
    "transferPetitionclause": " "
  },
  {
    "applicationNumber": "1020200127054",
    "receiptSendSerialNumber": "1",
    "receiptSendNumber": "112020104017278",
    "petitionclauseNumber": "7",
    "changeTypeCode": "I",
    "changeTypeName": "신규",
    "petitionclause": "제 1항에 있어서,<br />상기 용액 중합 스티렌-부타디엔 고무의 중량 평균 분자량(Mw)은 70만 내지 90만 g/mol인 타이어 트레드용 고무 조성물.",
    "transferReceiptDocNumber": " ",
    "transferPetitionclause": " "
  },
  {
    "applicationNumber": "1020200127054",
    "receiptSendSerialNumber": "1",
    "receiptSendNumber": "112020104017278",
    "petitionclauseNumber": "8",
    "changeTypeCode": "I",
    "changeTypeName": "신규",
    "petitionclause": "제 1항에 있어서,<br />상기 용액 중합 스티렌-부타디엔 고무의 유리전이온도(Tg)는 -35 내지 -15℃인 타이어 트레드용 고무 조성물.",
    "transferReceiptDocNumber": " ",
    "transferPetitionclause": " "
  },
  {
    "applicationNumber": "1020200127054",
    "receiptSendSerialNumber": "1",
    "receiptSendNumber": "112020104017278",
    "petitionclauseNumber": "9",
    "changeTypeCode": "I",
    "changeTypeName": "신규",
    "petitionclause": "제 1항에 있어서,<br />가소제 10 내지 50 중량부를 더 포함하되,<br />상기 가소제는, 연화점이 95 내지 115℃인 탄화수소계 수지(Resin)를 포함하는 타이어 트레드용 고무 조성물.",
    "transferReceiptDocNumber": " ",
    "transferPetitionclause": " "
  },
  {
    "applicationNumber": "1020200127054",
    "receiptSendSerialNumber": "1",
    "receiptSendNumber": "112020104017278",
    "petitionclauseNumber": "10",
    "changeTypeCode": "I",
    "changeTypeName": "신규",
    "petitionclause": "제 1항에 있어서,<br />가류제를 더 포함하는 타이어 트레드용 고무 조성물.",
    "transferReceiptDocNumber": " ",
    "transferPetitionclause": " "
  },
  {
    "applicationNumber": "1020200127054",
    "receiptSendSerialNumber": "1",
    "receiptSendNumber": "112020104017278",
    "petitionclauseNumber": "11",
    "changeTypeCode": "I",
    "changeTypeName": "신규",
    "petitionclause": "제 10항에 있어서,<br />가류촉진제 0.5 내지 2.5 중량부를 더 포함하는 타이어 트레드용 고무 조성물.",
    "transferReceiptDocNumber": " ",
    "transferPetitionclause": " "
  },
  {
    "applicationNumber": "1020200127054",
    "receiptSendSerialNumber": "1",
    "receiptSendNumber": "112020104017278",
    "petitionclauseNumber": "12",
    "changeTypeCode": "I",
    "changeTypeName": "신규",
    "petitionclause": "제 1항 내지 제 11항 중 어느 하나에 따른 타이어 트레드용 고무 조성물을 포함하는 타이어.<br /><br />",
    "transferReceiptDocNumber": " ",
    "transferPetitionclause": " "
  },
  {
    "applicationNumber": "1020200127054",
    "receiptSendSerialNumber": "2",
    "receiptSendNumber": "112022002393117",
    "petitionclauseNumber": "1",
    "changeTypeCode": "A",
    "changeTypeName": "수정",
    "petitionclause": "원료 고무 100 중량부; 및<br />보강성 충진제 90 내지 140 중량부를 포함하되,<br />상기 원료 고무는, <br />고시스 네오디뮴 부타디엔 고무(Nd-BR) 25 내지 65 중량부, 고기능성 리튬 부타디엔 고무(Functionalized Li-BR) 5 내지 45 중량부, 및 실리카로 변성되지 않은 용액 중합 스티렌-부타디엔 고무 20 내지 50 중량부를 포함하고,<br />상기 고시스 네오디뮴 부타디엔 고무는 시스 함량이 96% 이상이고, 중량 평균 분자량(Mw)이 30만 내지 60만 g/mol이고,<br />상기 고기능성 리튬 부타디엔 고무는 비닐(vinyl) 함량이 10 내지 40 중량%이고, 중량 평균 분자량(Mw)이 10만 내지 30만 g/mol이고,<br />상기 실리카로 변성되지 않은 용액 중합 스티렌-부타디엔 고무는, 스티렌 함량이 20 내지 40중량% 및 비닐 함량이 10 내지 40 중량%를 포함하는<br />타이어 트레드용 고무 조성물.",
    "transferReceiptDocNumber": "112020104017278",
    "transferPetitionclause": "원료 고무 100 중량부; 및<br />보강성 충진제 90 내지 140 중량부를 포함하되,<br />상기 원료 고무는, <br />고시스 네오디뮴 부타디엔 고무(Nd-BR) 25 내지 65 중량부, 고기능성 리튬 부타디엔 고무(Functionalized Li-BR) 5 내지 45 중량부, 및 <Ins>실리카로 변성되지 않은 </Ins>용액 중합 스티렌-부타디엔 고무 20 내지 50중량부를 포함하<Ins>고,<br />상기 고시스 네오디뮴 부타디엔 고무</Ins>는 <Ins>시스 함량이 96% 이상이고, 중량 평균 분자량(Mw)이 30만 내지 60만 g/mol이고,<br />상기 고기능성 리튬 부타디엔 고무는 비닐(vinyl) 함량이 10 내지 40 중량%이고, 중량 평균 분자량(Mw)이 10만 내지 30만 g/mol이고,<br />상기 실리카로 변성되지 않은 용액 중합 스티렌-부타디엔 고무는, 스티렌 함량이 20 내지 40중량% 및 비닐 함량이 10 내지 40 중량%를 포함하는<br /></Ins>타이어 트레드용 고무 조성물."
  },
  {
    "applicationNumber": "1020200127054",
    "receiptSendSerialNumber": "2",
    "receiptSendNumber": "112022002393117",
    "petitionclauseNumber": "2",
    "changeTypeCode": "D",
    "changeTypeName": "삭제",
    "petitionclause": " ",
    "transferReceiptDocNumber": " ",
    "transferPetitionclause": " "
  },
  {
    "applicationNumber": "1020200127054",
    "receiptSendSerialNumber": "2",
    "receiptSendNumber": "112022002393117",
    "petitionclauseNumber": "3",
    "changeTypeCode": "D",
    "changeTypeName": "삭제",
    "petitionclause": " ",
    "transferReceiptDocNumber": " ",
    "transferPetitionclause": " "
  },
  {
    "applicationNumber": "1020200127054",
    "receiptSendSerialNumber": "2",
    "receiptSendNumber": "112022002393117",
    "petitionclauseNumber": "5",
    "changeTypeCode": "D",
    "changeTypeName": "삭제",
    "petitionclause": " ",
    "transferReceiptDocNumber": " ",
    "transferPetitionclause": " "
  },
  {
    "applicationNumber": "1020200127054",
    "receiptSendSerialNumber": "2",
    "receiptSendNumber": "112022002393117",
    "petitionclauseNumber": "6",
    "changeTypeCode": "D",
    "changeTypeName": "삭제",
    "petitionclause": " ",
    "transferReceiptDocNumber": " ",
    "transferPetitionclause": " "
  },
  {
    "applicationNumber": "1020200127054",
    "receiptSendSerialNumber": "2",
    "receiptSendNumber": "112022002393117",
    "petitionclauseNumber": "12",
    "changeTypeCode": "A",
    "changeTypeName": "수정",
    "petitionclause": "제 1항, 제4항, 제7항 내지 제 11항 중 어느 하나에 따른 타이어 트레드용 고무 조성물을 포함하는 타이어.<br /><br /><br />",
    "transferReceiptDocNumber": "112020104017278",
    "transferPetitionclause": "제 1항<Ins>, 제4항, 제7항</Ins> 내지 제 11항 중 어느 하나에 따른 타이어 트레드용 고무 조성물을 포함하는 타이어.<br /><br /><Ins><br /></Ins>"
  }
]