{
  "meta": {
    "출원번호": "10-2023-0142654",
    "출원일자": "2023.10.24",
    "발명의명칭": "트럭버스 후륜용 타이어",
    "발송번호": "9-5-2025-060760877",
    "발송일자": "2025.06.26",
    "제출기일": "2025.08.26",
    "출원인": "한국타이어앤테크놀로지 주식회사",
    "대리인": "한상수",
    "발명자": [
      "천윤창"
    ],
    "인용발명": [
      "공개특허공보 제10-2021-0034306호(2021.03.30.)",
      "공개특허공보 제10-2015-0082486호(2015.07.15.)"
    ]
  },
  "심사결과": {
    "심사대상청구항": "제1-5항",
    "거절이유표": [
      {
        "순번": "1",
        "거절이유가 있는 부분": "청구항 제1항, 제3항 내지 제4항",
        "관련 법조항": "특허법 제29조제1항제2호"
      },
      {
        "순번": "2",
        "거절이유가 있는 부분": "청구항 전항",
        "관련 법조항": "특허법 제29조제2항"
      }
    ]
  },
  "구체적인거절이유": {
    "sections": [
      {
        "header": "1. 이 출원의 청구범위의 청구항 제1항, 제3항 내지 제4항에 기재된 발명은 아래와 같이 그",
        "content": "출원 전에 국내 또는 국외에서 반포된 간행물에 게재된 발명이거나 전기통신회선을 통하여\n공중이 이용가능하게 된 발명이므로 특허법 제29조제1항제2호에 해당되어 특허를 받을 수 없습니다.\n￭ 인용발명 1: 공개특허공보 제10-2021-0034306호(2021.03.30.)",
        "비교표": null
      },
      {
        "header": "1-1. 이 출원 발명과 인용발명 1은 모두 타이어 보강 구조에 관한 발명으로서 기술 분야가",
        "content": "서로 동일하고, 아래의 대비표에서 보는 바와 같이, 청구항 1 발명(독립항)은 인용발명 1과 일부\n표현상의 차이가 있을 뿐 동일한 발명입니다.",
        "비교표": null
      },
      {
        "header": "1-2. 청구항 3-4 발명에 부가된 특징은 인용발명 1(식별번호 16, 도면 1 참조)의 벨트층(40)은",
        "content": "카카스층(30)과 인접하여 형성되는 제1 벨트(41)부터 트레드부(10)를 향해 순차적으로 적층되는\n제2 벨트(42), 제3 벨트(43), 제4 벨트(44)로 구성된 점 및 아라미드 코드층(50)이 제2 벨트\n(42)와 제3 벨트(43) 사이에 배치되는 특징과 일부 표현상의 차이가 있을 뿐 동일한 구성입 니다.\n따라서 청구항 3-4 발명은 인용발명 1과 일부 표현상의 차이가 있을 뿐 동일한 발명입니다.",
        "비교표": null
      },
      {
        "header": "2. 이 출원의 청구범위의 청구항 전항에 기재된 발명은 아래와 같이 그 출원 전에 이 발명",
        "content": "이 속하는 기술분야에서 통상의 지식을 가진 사람이 쉽게 발명할 수 있는 것이므로 특허법\n제29조제2항에 따라 특허를 받을 수 없습니다.\n첨부1  공개특허공보 제10-2021-0034306호(2021.03.30.) 1부.\n첨부2  공개특허공보 제10-2015-0082486호(2015.07.15.) 1부.  끝.\n￭ 인용발명 1: 공개특허공보 제10-2021-0034306호(2021.03.30.)\n￭ 인용발명 2: 공개특허공보 제10-2015-0082486호(2015.07.15.)",
        "비교표": {
          "원본_헤더": [
            "구성",
            "청구항 1 발명",
            "인용발명 1 (식별번호 16-17, 도면 1 참조)",
            "비고"
          ],
          "rows": [
            {
              "구성": "1",
              "청구항 1 발명": "노면과 접지되는 트레드부",
              "인용발명 1 (식별번호 16-17, 도면 1 참조)": "노면과 접촉하는 트레드부(10)",
              "비고": "동일"
            },
            {
              "구성": "2",
              "청구항 1 발명": "타이어의 골격을 이루는 카카스부",
              "인용발명 1 (식별번호 16-17, 도면 1 참조)": "카카스층(30)",
              "비고": "동일"
            },
            {
              "구성": "3",
              "청구항 1 발명": "상기 트레드부와 상기 카카스부 사이 에 마련되는 벨트부",
              "인용발명 1 (식별번호 16-17, 도면 1 참조)": "트레드부(10)와 카카스층(30) 사이에 마련된 벨트층(40)",
              "비고": "동일"
            },
            {
              "구성": "4",
              "청구항 1 발명": "상기 벨트부의 내측에 형성되는 코일부",
              "인용발명 1 (식별번호 16-17, 도면 1 참조)": "벨트층(40)을 구성하는 제2 벨트(42) 와 제3 벨트(43) 사이에 구성된 아라 미드 코드층(50)",
              "비고": "동일"
            },
            {
              "구성": "도면",
              "청구항 1 발명": "",
              "인용발명 1 (식별번호 16-17, 도면 1 참조)": "",
              "비고": ""
            }
          ]
        }
      },
      {
        "header": "2-1. 앞서 “거절이유 1.”에서 살펴본 바와 같이, 청구항 1, 3-4 발명은 인용발명 1과 기술 분",
        "content": "야가 서로 동일하고, 표현상의 차이가 있을 뿐 기술적 구성이 실질적으로 동일하므로 통상의\n기술자가 인용발명 1로부터 쉽게 발명할 수 있습니다.",
        "비교표": null
      },
      {
        "header": "2-2. 청구항 2 발명에 부가된 특징은 인용발명 2(식별번호 27, 도면 1 참조)의 벨트층(14)에",
        "content": "구성된 보강층(145)이 코트 고무로 피복된 스틸제의 벨트 코드를 나선상으로 감아 돌리는\n구성으로부터 통상의 기술자가 쉽게 도출하여 구성할 수 있습니다. 한편, 인용발명 2는 타이어\n보강 구조에 관한 발명으로서, 이 출원 및 인용발명 1과 기술분야 및 주요 해결과제가 동일\n하므로, 통상의 기술자가 인용발명 1에 인용발명 2의 구조적 특징을 부가하여, 이 출원 발명을\n구현함에 있어서 특별한 기술적 어려움이나 구조적 제약 사항이 없습니다.\n따라서 청구항 2 발명은 통상의 기술자가 인용발명 1-2로부터 쉽게 발명할 수 있습니다.",
        "비교표": null
      },
      {
        "header": "2-3. 청구항 5 발명에 부가된 특징은 인용발명 1(식별번호 50-52, 도면 1 참조)의 단면폭이",
        "content": "445mm, 편평비 50, 22,5인치의 슈퍼 싱글 사이즈의 트럭 버스용 래디얼 타이어인 점으로\n부터 통상의 기술자가 쉽게 도출하여 구성할 수 있습니다.\n따라서 청구항 5 발명은 통상의 기술자가 인용발명 1로부터 쉽게 발명할 수 있습니다.",
        "비교표": null
      }
    ]
  },
  "첨부": [
    "공개특허공보 제10-2021-0034306호(2021.03.30.) 1부.",
    "공개특허공보 제10-2015-0082486호(2015.07.15.) 1부."
  ]
}